pydate40k/Date40k.py
pydate40k/__init__.py
pydate40k-0.1.dist-info/LICENSE
pydate40k-0.1.dist-info/METADATA
pydate40k-0.1.dist-info/WHEEL
pydate40k-0.1.dist-info/top_level.txt
pydate40k-0.1.dist-info/RECORD
