Metadata-Version: 2.1
Name: pydate40k
Version: 0.1
Summary: Return a date in the format of the Imperial Calendar
Home-page: https://github.com/UltimatePancake/pydate40k
Author: Pier Gaetani
Author-email: pier.gaetani@gmail.com
License: MIT
Platform: UNKNOWN
Classifier: Development Status :: 3 - Alpha
Classifier: Programming Language :: Python :: 3.7
Classifier: License :: OSI Approved :: MIT License
Classifier: Operating System :: OS Independent
Requires-Python: >=3.7
